windbell/__init__.py
windbell/lib.py
windbell/utils.py
windbell/cli/__init__.py
windbell/cli/dev.py
windbell/cli/init.py
windbell/cli/send.py
windbell/core/__init__.py
windbell/core/exceptions.py
windbell/core/mail.py
windbell/core/windfile.py
windbell/etc/windfile.sample
windbell/etc/dev/index.html
windbell/etc/dev/assets/css/main.css
windbell/etc/dev/assets/js/app.js
windbell-0.1.4.dist-info/LICENSE
windbell-0.1.4.dist-info/METADATA
windbell-0.1.4.dist-info/WHEEL
windbell-0.1.4.dist-info/entry_points.txt
windbell-0.1.4.dist-info/top_level.txt
windbell-0.1.4.dist-info/RECORD
