Metadata-Version: 2.1
Name: windbell
Version: 0.1.4
Summary: Fast email delivery in the wind.
Home-page: https://github.com/HawkinsZhao/windbell
Author: Hawkins Zhao
Author-email: hawkinszhao@outlook.com
License: MIT License
Requires-Dist: pystache (>=0.5.4)
Requires-Dist: setuptools (>=40.6.3)
Requires-Dist: tornado (>=5.0.0)
Requires-Dist: PyYAML (>=3.13)
Requires-Dist: premailer (>=3.4.0)
